ghonn_models_pytorch/__init__.py
ghonn_models_pytorch/core/__init__.py
ghonn_models_pytorch/core/ghonn.py
ghonn_models_pytorch/core/ghonu.py
ghonn_models_pytorch/core/honn.py
ghonn_models_pytorch/core/honu.py
ghonn_models_pytorch/core/utils.py
ghonn_models_pytorch/datasets/__init__.py
ghonn_models_pytorch/datasets/collections.py
ghonn_models_pytorch/datasets/data_loaders.py
ghonn_models_pytorch-0.1.1.dist-info/licenses/LICENSE
ghonn_models_pytorch-0.1.1.dist-info/METADATA
ghonn_models_pytorch-0.1.1.dist-info/WHEEL
ghonn_models_pytorch-0.1.1.dist-info/top_level.txt
ghonn_models_pytorch-0.1.1.dist-info/RECORD
