Metadata-Version: 2.4
Name: ghonn_models_pytorch
Version: 0.1.1
Summary: Gated Higher Order Neural Networks models. PyTorch.
Author-email: Ondrej Budik <obudik@jcu.cz>
Project-URL: Homepage, https://gmp.readthedocs.io/en/latest/
Project-URL: Repository, https://github.com/carnosi/ghonn_models_pytorch
Classifier: Programming Language :: Python :: 3
Classifier: Programming Language :: Python :: 3.9
Classifier: Programming Language :: Python :: 3.10
Classifier: Programming Language :: Python :: 3.11
Classifier: Programming Language :: Python :: 3.12
Classifier: Programming Language :: Python :: Implementation :: PyPy
Classifier: Operating System :: OS Independent
Requires-Python: >=3.9
License-File: LICENSE
Requires-Dist: torch~=2.7.0
Requires-Dist: numpy~=2.2.0
Requires-Dist: pandas~=2.2.0
Provides-Extra: docs
Requires-Dist: sphinx; extra == "docs"
Requires-Dist: autodocsumm; extra == "docs"
Requires-Dist: sphinx-book-theme; extra == "docs"
Provides-Extra: dev
Requires-Dist: ruff>=0.11; extra == "dev"
Requires-Dist: mypy; extra == "dev"
Requires-Dist: setuptools; extra == "dev"
Requires-Dist: pylint; extra == "dev"
Requires-Dist: build; extra == "dev"
Provides-Extra: examples
Requires-Dist: matplotlib; extra == "examples"
Requires-Dist: jupyter; extra == "examples"
Requires-Dist: sklearn; extra == "examples"
Requires-Dist: tqdm; extra == "examples"
Dynamic: license-file
